[
 {
   "OBJECTID": 1,
   "Shape_Length": 4326.700516,
   "roadId": 4,
   "cityId": 1,
   "roadName": "Alrabea"
 },
 {
   "OBJECTID": 2,
   "Shape_Length": 6314.544095,
   "roadId": 1,
   "cityId": 1,
   "roadName": "Talaat Mostafa"
 },
 {
   "OBJECTID": 3,
   "Shape_Length": 4606.927899,
   "roadId": 5,
   "cityId": 1,
   "roadName": "Madinty"
 },
 {
   "OBJECTID": 4,
   "Shape_Length": 5618.291188,
   "roadId": 2,
   "cityId": 1,
   "roadName": " Alwady"
 },
 {
   "OBJECTID": 5,
   "Shape_Length": 3783.017578,
   "roadId": 6,
   "cityId": 1,
   "roadName": "Talaat Mostafa-2"
 },
 {
   "OBJECTID": 6,
   "Shape_Length": 1700.448423,
   "roadId": 3,
   "cityId": 1,
   "roadName": "Alzohor"
 }
]